{
  "$type": "Comindware.Platform.Contracts.ToolbarModel, Comindware.Platform.Contracts",
  "GlobalAlias": {
    "$type": "Comindware.Platform.Contracts.GlobalAlias, Comindware.Platform.Contracts",
    "Type": "Toolbar",
    "Owner": "Priemynarabotu",
    "Alias": "toolbar322tyutyu2"
  },
  "Name": "Панель инструментов toolbar3222",
  "IsDefaultForLists": false,
  "IsDefaultForForms": false,
  "IsDefaultForProcess": false,
  "IsDefaultForProcessDesigner": false,
  "IsDefaultForTaskLists": false
}