{
  "$type": "Comindware.Platform.Contracts.AttributeModel, Comindware.Platform.Contracts",
  "GlobalAlias": {
    "$type": "Comindware.Platform.Contracts.GlobalAlias, Comindware.Platform.Contracts",
    "Type": "Attribute",
    "Owner": "Priemynarabotu",
    "Alias": "Rukovoditel"
  },
  "Type": "Account",
  "Format": "Undefined",
  "Name": "Руководитель",
  "IsSystem": false,
  "IsDisabled": false,
  "IsUnique": false,
  "IsIndexed": false,
  "IsTracked": false,
  "IsMultiValue": false,
  "IsTitle": false,
  "IsMandatory": false,
  "IsOwnership": false,
  "IsCalculated": false,
  "InstanceGlobalAlias": {
    "$type": "Comindware.Platform.Contracts.GlobalAlias, Comindware.Platform.Contracts",
    "Type": "RecordTemplate",
    "Alias": "_Account"
  },
  "ImageColorType": "Original",
  "ImagePreserveAspectRatio": false
}